awscreds/__init__.py
awscreds/cli.py
aws_credentials_clipboard_updater-1.0.7.dist-info/METADATA
aws_credentials_clipboard_updater-1.0.7.dist-info/WHEEL
aws_credentials_clipboard_updater-1.0.7.dist-info/entry_points.txt
aws_credentials_clipboard_updater-1.0.7.dist-info/licenses/LICENSE
aws_credentials_clipboard_updater-1.0.7.dist-info/RECORD
