Metadata-Version: 2.4
Name: aws-credentials-clipboard-updater
Version: 1.0.7
Summary: A command-line utility to manage AWS credentials from clipboard or data
Project-URL: Homepage, https://github.com/vavasilva/aws-credentials-clipboard-updater
Project-URL: Repository, https://github.com/vavasilva/aws-credentials-clipboard-updater
Project-URL: Issues, https://github.com/vavasilva/aws-credentials-clipboard-updater/issues
Author-email: Wagner Silva <vavasilva@users.noreply.github.com>
License-File: LICENSE
Keywords: aws,cli,clipboard,credentials,devops
Classifier: Development Status :: 5 - Production/Stable
Classifier: Intended Audience :: Developers
Classifier: License :: OSI Approved :: MIT License
Classifier: Operating System :: OS Independent
Classifier: Programming Language :: Python :: 3
Classifier: Programming Language :: Python :: 3.7
Classifier: Programming Language :: Python :: 3.8
Classifier: Programming Language :: Python :: 3.9
Classifier: Programming Language :: Python :: 3.10
Classifier: Programming Language :: Python :: 3.11
Classifier: Programming Language :: Python :: 3.12
Classifier: Topic :: Software Development :: Libraries :: Python Modules
Classifier: Topic :: System :: Systems Administration
Requires-Python: >=3.7
Requires-Dist: click
